Metadata-Version: 2.1
Name: simpleprocessbar
Version: 1.0.2
Summary: a very very simple processbar
Home-page: UNKNOWN
Author: linle
Author-email: linle861021@163.com
License: MIT
Platform: UNKNOWN
Requires-Python: >=3.6
